{
    "cipher": "ballet_p128_k256_o128_r2",
    "model_type": "xor_linear",
    "solver_name": "PARKISSAT_EXT",
    "solving_time_seconds": 1.0879230499267578,
    "memory_megabytes": 0,
    "components_values": {
        "plaintext": {
            "value": "0x04000000008000000080000000000000"
        },
        "key_0_1": {
            "value": "0x00000000"
        },
        "key_0_8": {
            "value": "0x00000000"
        },
        "key_1_1": {
            "value": "0x00000001"
        },
        "key_1_8": {
            "value": "0x00000000"
        },
        "xor_0_0_o": {
            "value": "0x00800000",
            "weight": 0
        },
        "xor_0_0_i": {
            "value": "0x00800000",
            "weight": 0
        },
        "xor_0_1_o": {
            "value": "0x00000000",
            "weight": 0
        },
        "xor_0_1_i": {
            "value": "0x00000000",
            "weight": 0
        },
        "rot_0_2_o": {
            "value": "0x00000001",
            "weight": 0
        },
        "rot_0_2_i": {
            "value": "0x04000000",
            "weight": 0
        },
        "rot_0_3_o": {
            "value": "0x00000001",
            "weight": 0
        },
        "rot_0_3_i": {
            "value": "0x00800000",
            "weight": 0
        },
        "modadd_0_4_o": {
            "value": "0x00000001",
            "weight": 0
        },
        "modadd_0_4_i": {
            "value": "0x00000001",
            "weight": 0
        },
        "rot_0_5_o": {
            "value": "0x00000000",
            "weight": 0
        },
        "rot_0_5_i": {
            "value": "0x00000000",
            "weight": 0
        },
        "rot_0_6_o": {
            "value": "0x00000000",
            "weight": 0
        },
        "rot_0_6_i": {
            "value": "0x00000000",
            "weight": 0
        },
        "modadd_0_7_o": {
            "value": "0x00000000",
            "weight": 0
        },
        "modadd_0_7_i": {
            "value": "0x00000000",
            "weight": 0
        },
        "xor_0_8_o": {
            "value": "0x00000000",
            "weight": 0
        },
        "xor_0_8_i": {
            "value": "0x00000000",
            "weight": 0
        },
        "intermediate_output_0_10_o": {
            "value": "0x00000000000000010000000000000000",
            "weight": 0
        },
        "intermediate_output_0_10_i": {
            "value": "0x00000000000000010000000000000000",
            "weight": 0
        },
        "xor_1_0_o": {
            "value": "0x00000000",
            "weight": 0
        },
        "xor_1_0_i": {
            "value": "0x00000000",
            "weight": 0
        },
        "xor_1_1_o": {
            "value": "0x00000001",
            "weight": 0
        },
        "xor_1_1_i": {
            "value": "0x00000001",
            "weight": 0
        },
        "rot_1_2_o": {
            "value": "0x00000000",
            "weight": 0
        },
        "rot_1_2_i": {
            "value": "0x00000000",
            "weight": 0
        },
        "rot_1_3_o": {
            "value": "0x00000000",
            "weight": 0
        },
        "rot_1_3_i": {
            "value": "0x00000000",
            "weight": 0
        },
        "modadd_1_4_o": {
            "value": "0x00000000",
            "weight": 0
        },
        "modadd_1_4_i": {
            "value": "0x00000000",
            "weight": 0
        },
        "rot_1_5_o": {
            "value": "0x00000000",
            "weight": 0
        },
        "rot_1_5_i": {
            "value": "0x00000000",
            "weight": 0
        },
        "rot_1_6_o": {
            "value": "0x00000000",
            "weight": 0
        },
        "rot_1_6_i": {
            "value": "0x00000000",
            "weight": 0
        },
        "modadd_1_7_o": {
            "value": "0x00000000",
            "weight": 0
        },
        "modadd_1_7_i": {
            "value": "0x00000000",
            "weight": 0
        },
        "xor_1_8_o": {
            "value": "0x00000000",
            "weight": 0
        },
        "xor_1_8_i": {
            "value": "0x00000000",
            "weight": 0
        },
        "cipher_output_1_10_o": {
            "value": "0x00000000000000010000000000000000",
            "weight": 0
        },
        "cipher_output_1_10_i": {
            "value": "0x00000000000000010000000000000000",
            "weight": 0
        }
    },
    "total_weight": 0.0,
    "status": "SATISFIABLE",
    "building_time_seconds": 0.009133338928222656,
    "test_name": "find_lowest_weight_xor_linear_trail"
}