{
    "cipher": "ballet_p256_k256_o256_r9",
    "model_type": "xor_linear",
    "solver_name": "PARKISSAT_EXT",
    "solving_time_seconds": 124490.870439291,
    "memory_megabytes": 0,
    "components_values": {
        "plaintext": {
            "value": "0x0400000000000000008400000000000c00840000000000000002000000000000"
        },
        "key_0_1": {
            "value": "0x000000000000000c"
        },
        "key_0_8": {
            "value": "0x0000000000000000"
        },
        "key_1_1": {
            "value": "0x0000000000000000"
        },
        "key_1_8": {
            "value": "0x0000000000000000"
        },
        "key_2_1": {
            "value": "0x0000000000000200"
        },
        "key_2_8": {
            "value": "0x0000000000000000"
        },
        "key_3_1": {
            "value": "0x0000000000000040"
        },
        "key_3_8": {
            "value": "0x0000000000000040"
        },
        "key_4_1": {
            "value": "0x000000000000c0c8"
        },
        "key_4_8": {
            "value": "0x00000000000000c8"
        },
        "key_5_1": {
            "value": "0x0000000000000000"
        },
        "key_5_8": {
            "value": "0x0000000000201800"
        },
        "key_6_1": {
            "value": "0x0000000000600000"
        },
        "key_6_8": {
            "value": "0x0000000000042000"
        },
        "key_7_1": {
            "value": "0x0000000000006000"
        },
        "key_7_8": {
            "value": "0x0000001808006000"
        },
        "key_8_1": {
            "value": "0x0000002008008800"
        },
        "key_8_8": {
            "value": "0x0000002308008800"
        },
        "xor_0_0_o": {
            "value": "0x0084000000000000",
            "weight": 0
        },
        "xor_0_0_i": {
            "value": "0x0084000000000000",
            "weight": 0
        },
        "xor_0_1_o": {
            "value": "0x000000000000000c",
            "weight": 0
        },
        "xor_0_1_i": {
            "value": "0x000000000000000c",
            "weight": 0
        },
        "rot_0_2_o": {
            "value": "0x0000000000000001",
            "weight": 0
        },
        "rot_0_2_i": {
            "value": "0x0400000000000000",
            "weight": 0
        },
        "rot_0_3_o": {
            "value": "0x0000000000000001",
            "weight": 0
        },
        "rot_0_3_i": {
            "value": "0x0080000000000000",
            "weight": 0
        },
        "modadd_0_4_o": {
            "value": "0x0000000000000001",
            "weight": 0
        },
        "modadd_0_4_i": {
            "value": "0x0000000000000001",
            "weight": 0
        },
        "rot_0_5_o": {
            "value": "0x0000000000000001",
            "weight": 0
        },
        "rot_0_5_i": {
            "value": "0x0002000000000000",
            "weight": 0
        },
        "rot_0_6_o": {
            "value": "0x0000000000000001",
            "weight": 0
        },
        "rot_0_6_i": {
            "value": "0x0004000000000000",
            "weight": 0
        },
        "modadd_0_7_o": {
            "value": "0x0000000000000001",
            "weight": 0
        },
        "modadd_0_7_i": {
            "value": "0x0000000000000001",
            "weight": 0
        },
        "xor_0_8_o": {
            "value": "0x0000000000000000",
            "weight": 0
        },
        "xor_0_8_i": {
            "value": "0x0000000000000000",
            "weight": 0
        },
        "intermediate_output_0_10_o": {
            "value": "0x000000000000000c000000000000000100000000000000010000000000000000",
            "weight": 0
        },
        "intermediate_output_0_10_i": {
            "value": "0x000000000000000c000000000000000100000000000000010000000000000000",
            "weight": 0
        },
        "xor_1_0_o": {
            "value": "0x0000000000000001",
            "weight": 0
        },
        "xor_1_0_i": {
            "value": "0x0000000000000001",
            "weight": 0
        },
        "xor_1_1_o": {
            "value": "0x0000000000000000",
            "weight": 0
        },
        "xor_1_1_i": {
            "value": "0x0000000000000000",
            "weight": 0
        },
        "rot_1_2_o": {
            "value": "0x0000000000000300",
            "weight": 0
        },
        "rot_1_2_i": {
            "value": "0x000000000000000c",
            "weight": 0
        },
        "rot_1_3_o": {
            "value": "0x0000000000000200",
            "weight": 0
        },
        "rot_1_3_i": {
            "value": "0x0000000000000001",
            "weight": 0
        },
        "modadd_1_4_o": {
            "value": "0x0000000000000200",
            "weight": 1
        },
        "modadd_1_4_i": {
            "value": "0x0000000000000300",
            "weight": 0
        },
        "rot_1_5_o": {
            "value": "0x0000000000000000",
            "weight": 0
        },
        "rot_1_5_i": {
            "value": "0x0000000000000000",
            "weight": 0
        },
        "rot_1_6_o": {
            "value": "0x0000000000000000",
            "weight": 0
        },
        "rot_1_6_i": {
            "value": "0x0000000000000000",
            "weight": 0
        },
        "modadd_1_7_o": {
            "value": "0x0000000000000000",
            "weight": 0
        },
        "modadd_1_7_i": {
            "value": "0x0000000000000000",
            "weight": 0
        },
        "xor_1_8_o": {
            "value": "0x0000000000000000",
            "weight": 0
        },
        "xor_1_8_i": {
            "value": "0x0000000000000000",
            "weight": 0
        },
        "intermediate_output_1_10_o": {
            "value": "0x0000000000000000000000000000020000000000000000000000000000000000",
            "weight": 0
        },
        "intermediate_output_1_10_i": {
            "value": "0x0000000000000000000000000000020000000000000000000000000000000000",
            "weight": 0
        },
        "xor_2_0_o": {
            "value": "0x0000000000000000",
            "weight": 0
        },
        "xor_2_0_i": {
            "value": "0x0000000000000000",
            "weight": 0
        },
        "xor_2_1_o": {
            "value": "0x0000000000000200",
            "weight": 0
        },
        "xor_2_1_i": {
            "value": "0x0000000000000200",
            "weight": 0
        },
        "rot_2_2_o": {
            "value": "0x0000000000000000",
            "weight": 0
        },
        "rot_2_2_i": {
            "value": "0x0000000000000000",
            "weight": 0
        },
        "rot_2_3_o": {
            "value": "0x0000000000000000",
            "weight": 0
        },
        "rot_2_3_i": {
            "value": "0x0000000000000000",
            "weight": 0
        },
        "modadd_2_4_o": {
            "value": "0x0000000000000000",
            "weight": 0
        },
        "modadd_2_4_i": {
            "value": "0x0000000000000000",
            "weight": 0
        },
        "rot_2_5_o": {
            "value": "0x0000000000000000",
            "weight": 0
        },
        "rot_2_5_i": {
            "value": "0x0000000000000000",
            "weight": 0
        },
        "rot_2_6_o": {
            "value": "0x0000000000000000",
            "weight": 0
        },
        "rot_2_6_i": {
            "value": "0x0000000000000000",
            "weight": 0
        },
        "modadd_2_7_o": {
            "value": "0x0000000000000000",
            "weight": 0
        },
        "modadd_2_7_i": {
            "value": "0x0000000000000000",
            "weight": 0
        },
        "xor_2_8_o": {
            "value": "0x0000000000000000",
            "weight": 0
        },
        "xor_2_8_i": {
            "value": "0x0000000000000000",
            "weight": 0
        },
        "intermediate_output_2_10_o": {
            "value": "0x0000000000000200000000000000000000000000000000000000000000000000",
            "weight": 0
        },
        "intermediate_output_2_10_i": {
            "value": "0x0000000000000200000000000000000000000000000000000000000000000000",
            "weight": 0
        },
        "xor_3_0_o": {
            "value": "0x0000000000000040",
            "weight": 0
        },
        "xor_3_0_i": {
            "value": "0x0000000000000040",
            "weight": 0
        },
        "xor_3_1_o": {
            "value": "0x0000000000000040",
            "weight": 0
        },
        "xor_3_1_i": {
            "value": "0x0000000000000040",
            "weight": 0
        },
        "rot_3_2_o": {
            "value": "0x0000000000008000",
            "weight": 0
        },
        "rot_3_2_i": {
            "value": "0x0000000000000200",
            "weight": 0
        },
        "rot_3_3_o": {
            "value": "0x0000000000008000",
            "weight": 0
        },
        "rot_3_3_i": {
            "value": "0x0000000000000040",
            "weight": 0
        },
        "modadd_3_4_o": {
            "value": "0x000000000000c000",
            "weight": 1
        },
        "modadd_3_4_i": {
            "value": "0x0000000000008000",
            "weight": 0
        },
        "rot_3_5_o": {
            "value": "0x0000000000000000",
            "weight": 0
        },
        "rot_3_5_i": {
            "value": "0x0000000000000000",
            "weight": 0
        },
        "rot_3_6_o": {
            "value": "0x0000000000000000",
            "weight": 0
        },
        "rot_3_6_i": {
            "value": "0x0000000000000000",
            "weight": 0
        },
        "modadd_3_7_o": {
            "value": "0x0000000000000000",
            "weight": 0
        },
        "modadd_3_7_i": {
            "value": "0x0000000000000000",
            "weight": 0
        },
        "xor_3_8_o": {
            "value": "0x0000000000000040",
            "weight": 0
        },
        "xor_3_8_i": {
            "value": "0x0000000000000040",
            "weight": 0
        },
        "intermediate_output_3_10_o": {
            "value": "0x0000000000000040000000000000c00000000000000000000000000000000040",
            "weight": 0
        },
        "intermediate_output_3_10_i": {
            "value": "0x0000000000000040000000000000c00000000000000000000000000000000040",
            "weight": 0
        },
        "xor_4_0_o": {
            "value": "0x00000000000000c8",
            "weight": 0
        },
        "xor_4_0_i": {
            "value": "0x00000000000000c8",
            "weight": 0
        },
        "xor_4_1_o": {
            "value": "0x000000000000c0c8",
            "weight": 0
        },
        "xor_4_1_i": {
            "value": "0x000000000000c0c8",
            "weight": 0
        },
        "rot_4_2_o": {
            "value": "0x0000000000001000",
            "weight": 0
        },
        "rot_4_2_i": {
            "value": "0x0000000000000040",
            "weight": 0
        },
        "rot_4_3_o": {
            "value": "0x0000000000001000",
            "weight": 0
        },
        "rot_4_3_i": {
            "value": "0x0000000000000008",
            "weight": 0
        },
        "modadd_4_4_o": {
            "value": "0x0000000000001800",
            "weight": 1
        },
        "modadd_4_4_i": {
            "value": "0x0000000000001000",
            "weight": 0
        },
        "rot_4_5_o": {
            "value": "0x0000000000200000",
            "weight": 0
        },
        "rot_4_5_i": {
            "value": "0x0000000000000040",
            "weight": 0
        },
        "rot_4_6_o": {
            "value": "0x0000000000300000",
            "weight": 0
        },
        "rot_4_6_i": {
            "value": "0x00000000000000c0",
            "weight": 0
        },
        "modadd_4_7_o": {
            "value": "0x0000000000200000",
            "weight": 1
        },
        "modadd_4_7_i": {
            "value": "0x0000000000200000",
            "weight": 0
        },
        "xor_4_8_o": {
            "value": "0x00000000000000c8",
            "weight": 0
        },
        "xor_4_8_i": {
            "value": "0x00000000000000c8",
            "weight": 0
        },
        "intermediate_output_4_10_o": {
            "value": "0x000000000000c0c80000000000001800000000000020000000000000000000c8",
            "weight": 0
        },
        "intermediate_output_4_10_i": {
            "value": "0x000000000000c0c80000000000001800000000000020000000000000000000c8",
            "weight": 0
        },
        "xor_5_0_o": {
            "value": "0x0000000000001800",
            "weight": 0
        },
        "xor_5_0_i": {
            "value": "0x0000000000001800",
            "weight": 0
        },
        "xor_5_1_o": {
            "value": "0x0000000000000000",
            "weight": 0
        },
        "xor_5_1_i": {
            "value": "0x0000000000000000",
            "weight": 0
        },
        "rot_5_2_o": {
            "value": "0x0000000000303200",
            "weight": 0
        },
        "rot_5_2_i": {
            "value": "0x000000000000c0c8",
            "weight": 0
        },
        "rot_5_3_o": {
            "value": "0x0000000000323000",
            "weight": 0
        },
        "rot_5_3_i": {
            "value": "0x0000000000001918",
            "weight": 0
        },
        "modadd_5_4_o": {
            "value": "0x0000000000202000",
            "weight": 8
        },
        "modadd_5_4_i": {
            "value": "0x0000000000303200",
            "weight": 0
        },
        "rot_5_5_o": {
            "value": "0x0000000000640000",
            "weight": 0
        },
        "rot_5_5_i": {
            "value": "0x00000000000000c8",
            "weight": 0
        },
        "rot_5_6_o": {
            "value": "0x0000000000460000",
            "weight": 0
        },
        "rot_5_6_i": {
            "value": "0x0000000000000118",
            "weight": 0
        },
        "modadd_5_7_o": {
            "value": "0x0000000000440000",
            "weight": 2
        },
        "modadd_5_7_i": {
            "value": "0x0000000000640000",
            "weight": 0
        },
        "xor_5_8_o": {
            "value": "0x0000000000201800",
            "weight": 0
        },
        "xor_5_8_i": {
            "value": "0x0000000000201800",
            "weight": 0
        },
        "intermediate_output_5_10_o": {
            "value": "0x0000000000000000000000000020200000000000004400000000000000201800",
            "weight": 0
        },
        "intermediate_output_5_10_i": {
            "value": "0x0000000000000000000000000020200000000000004400000000000000201800",
            "weight": 0
        },
        "xor_6_0_o": {
            "value": "0x0000000000402000",
            "weight": 0
        },
        "xor_6_0_i": {
            "value": "0x0000000000402000",
            "weight": 0
        },
        "xor_6_1_o": {
            "value": "0x0000000000600000",
            "weight": 0
        },
        "xor_6_1_i": {
            "value": "0x0000000000600000",
            "weight": 0
        },
        "rot_6_2_o": {
            "value": "0x0000000000000000",
            "weight": 0
        },
        "rot_6_2_i": {
            "value": "0x0000000000000000",
            "weight": 0
        },
        "rot_6_3_o": {
            "value": "0x0000000000000000",
            "weight": 0
        },
        "rot_6_3_i": {
            "value": "0x0000000000000000",
            "weight": 0
        },
        "modadd_6_4_o": {
            "value": "0x0000000000000000",
            "weight": 0
        },
        "modadd_6_4_i": {
            "value": "0x0000000000000000",
            "weight": 0
        },
        "rot_6_5_o": {
            "value": "0x000000100c000000",
            "weight": 0
        },
        "rot_6_5_i": {
            "value": "0x0000000000201800",
            "weight": 0
        },
        "rot_6_6_o": {
            "value": "0x0000001008000000",
            "weight": 0
        },
        "rot_6_6_i": {
            "value": "0x0000000000402000",
            "weight": 0
        },
        "modadd_6_7_o": {
            "value": "0x0000001808000000",
            "weight": 2
        },
        "modadd_6_7_i": {
            "value": "0x000000100c000000",
            "weight": 0
        },
        "xor_6_8_o": {
            "value": "0x0000000000042000",
            "weight": 0
        },
        "xor_6_8_i": {
            "value": "0x0000000000042000",
            "weight": 0
        },
        "intermediate_output_6_10_o": {
            "value": "0x0000000000600000000000000000000000000018080000000000000000042000",
            "weight": 0
        },
        "intermediate_output_6_10_i": {
            "value": "0x0000000000600000000000000000000000000018080000000000000000042000",
            "weight": 0
        },
        "xor_7_0_o": {
            "value": "0x0000000000006000",
            "weight": 0
        },
        "xor_7_0_i": {
            "value": "0x0000000000006000",
            "weight": 0
        },
        "xor_7_1_o": {
            "value": "0x0000000000006000",
            "weight": 0
        },
        "xor_7_1_i": {
            "value": "0x0000000000006000",
            "weight": 0
        },
        "rot_7_2_o": {
            "value": "0x0000000018000000",
            "weight": 0
        },
        "rot_7_2_i": {
            "value": "0x0000000000600000",
            "weight": 0
        },
        "rot_7_3_o": {
            "value": "0x0000000010000000",
            "weight": 0
        },
        "rot_7_3_i": {
            "value": "0x0000000000080000",
            "weight": 0
        },
        "modadd_7_4_o": {
            "value": "0x0000000010000000",
            "weight": 1
        },
        "modadd_7_4_i": {
            "value": "0x0000000018000000",
            "weight": 0
        },
        "rot_7_5_o": {
            "value": "0x0000000210000000",
            "weight": 0
        },
        "rot_7_5_i": {
            "value": "0x0000000000042000",
            "weight": 0
        },
        "rot_7_6_o": {
            "value": "0x0000000218000000",
            "weight": 0
        },
        "rot_7_6_i": {
            "value": "0x0000000000086000",
            "weight": 0
        },
        "modadd_7_7_o": {
            "value": "0x0000000310000000",
            "weight": 2
        },
        "modadd_7_7_i": {
            "value": "0x0000000210000000",
            "weight": 0
        },
        "xor_7_8_o": {
            "value": "0x0000001808006000",
            "weight": 0
        },
        "xor_7_8_i": {
            "value": "0x0000001808006000",
            "weight": 0
        },
        "intermediate_output_7_10_o": {
            "value": "0x0000000000006000000000001000000000000003100000000000001808006000",
            "weight": 0
        },
        "intermediate_output_7_10_i": {
            "value": "0x0000000000006000000000001000000000000003100000000000001808006000",
            "weight": 0
        },
        "xor_8_0_o": {
            "value": "0x0000002018008800",
            "weight": 0
        },
        "xor_8_0_i": {
            "value": "0x0000002018008800",
            "weight": 0
        },
        "xor_8_1_o": {
            "value": "0x0000002008008800",
            "weight": 0
        },
        "xor_8_1_i": {
            "value": "0x0000002008008800",
            "weight": 0
        },
        "rot_8_2_o": {
            "value": "0x0000000000180000",
            "weight": 0
        },
        "rot_8_2_i": {
            "value": "0x0000000000006000",
            "weight": 0
        },
        "rot_8_3_o": {
            "value": "0x0000000000100000",
            "weight": 0
        },
        "rot_8_3_i": {
            "value": "0x0000000000000800",
            "weight": 0
        },
        "modadd_8_4_o": {
            "value": "0x0000000000100000",
            "weight": 1
        },
        "modadd_8_4_i": {
            "value": "0x0000000000180000",
            "weight": 0
        },
        "rot_8_5_o": {
            "value": "0x000c040030000000",
            "weight": 0
        },
        "rot_8_5_i": {
            "value": "0x0000001808006000",
            "weight": 0
        },
        "rot_8_6_o": {
            "value": "0x0008060020000000",
            "weight": 0
        },
        "rot_8_6_i": {
            "value": "0x0000002018008000",
            "weight": 0
        },
        "modadd_8_7_o": {
            "value": "0x0008040020000000",
            "weight": 3
        },
        "modadd_8_7_i": {
            "value": "0x000c040030000000",
            "weight": 0
        },
        "xor_8_8_o": {
            "value": "0x0000002308008800",
            "weight": 0
        },
        "xor_8_8_i": {
            "value": "0x0000002308008800",
            "weight": 0
        },
        "cipher_output_8_10_o": {
            "value": "0x0000000000100000000000200800880000000023080088000008040020000000",
            "weight": 0
        },
        "cipher_output_8_10_i": {
            "value": "0x0000000000100000000000200800880000000023080088000008040020000000",
            "weight": 0
        }
    },
    "total_weight": 23.0,
    "status": "SATISFIABLE",
    "building_time_seconds": 0.1595621109008789,
    "test_name": "find_lowest_weight_xor_linear_trail"
}